[
    {
        "code": "PROMPTPAY",
        "logo": "https://raw.githubusercontent.com/smlsoft/dedepos_template/main/img/qrcode/promptpay.jpeg",
        "qrnames": [
            {
                "code": "th",
                "name": "พร้อมเพย์"
            },
            {
                "code": "en",
                "name": "Promptpay"
            }
        ],
        "qrtype": 100
    },
    {
        "code": "KPLUSSHOP",
        "logo": "https://raw.githubusercontent.com/smlsoft/dedepos_template/main/img/qrcode/kplusshop.png",
        "qrnames": [
            {
                "code": "th",
                "name": "เคพลัสช็อป"
            },
            {
                "code": "en",
                "name": "K Plus Shop"
            }
        ],
        "qrtype": 101
    },
    {
        "code": "LUJENT",
        "logo": "https://raw.githubusercontent.com/smlsoft/dedepos_template/main/img/qrcode/lugent.jpeg",
        "qrnames": [
            {
                "code": "th",
                "name": "ลูเจ้น พร้อมเพย์"
            },
            {
                "code": "en",
                "name": "Lugent PromptPay"
            }
        ],
        "qrtype": 110
    },
    {
        "code": "ALIPAY",
        "logo": "https://raw.githubusercontent.com/smlsoft/dedepos_template/main/img/qrcode/alipay.jpeg",
        "qrnames": [
            {
                "code": "th",
                "name": "อาลีเพย์"
            },
            {
                "code": "en",
                "name": "Ali Pay"
            }
        ],
        "qrtype": 111
    },
    {
        "code": "TRUEMONEY",
        "logo": "https://raw.githubusercontent.com/smlsoft/dedepos_template/main/img/qrcode/truemoney.jpeg",
        "qrnames": [
            {
                "code": "th",
                "name": "ทรูมันนี่"
            },
            {
                "code": "en",
                "name": "True Money"
            }
        ],
        "qrtype": 112
    },
    {
        "code": "LINEPAY",
        "logo": "https://raw.githubusercontent.com/smlsoft/dedepos_template/main/img/qrcode/linepay.jpeg",
        "qrnames": [
            {
                "code": "th",
                "name": "ไลน์เพย์"
            },
            {
                "code": "en",
                "name": "Line Pay"
            }
        ],
        "qrtype": 113
    },
    {
        "code": "GBTHAIQR",
        "logo": "https://raw.githubusercontent.com/smlsoft/dedepos_template/main/img/qrcode/gb-pp.png",
        "qrnames": [
            {
                "code": "th",
                "name": "GB - พร้อมเพย์"
            },
            {
                "code": "en",
                "name": "GB - Promptpay"
            }
        ],
        "qrtype": 131
    },
    {
        "code": "GBTRUEMONEY",
        "logo": "https://raw.githubusercontent.com/smlsoft/dedepos_template/main/img/qrcode/truemoney.jpeg",
        "qrnames": [
            {
                "code": "th",
                "name": "GB - ทรูมันนี่"
            },
            {
                "code": "en",
                "name": "GB - True Money"
            }
        ],
        "qrtype": 132
    },
    {
        "code": "GBSHOPEEPAY",
        "logo": "https://raw.githubusercontent.com/smlsoft/dedepos_template/main/img/wallet/shopee.png",
        "qrnames": [
            {
                "code": "th",
                "name": "GB - ช้อปปี้เพย์"
            },
            {
                "code": "en",
                "name": "GB - Shopee Pay"
            }
        ],
        "qrtype": 133
    },
    {
        "code": "GBALIPAY",
        "logo": "https://raw.githubusercontent.com/smlsoft/dedepos_template/main/img/qrcode/alipay.jpeg",
        "qrnames": [
            {
                "code": "th",
                "name": "GB - อาลีเพย์"
            },
            {
                "code": "en",
                "name": "GB - Ali Pay"
            }
        ],
        "qrtype": 134
    },
    {
        "code": "GBWECHAT",
        "logo": "https://raw.githubusercontent.com/smlsoft/dedepos_template/main/img/qrcode/wechatpay.png",
        "qrnames": [
            {
                "code": "th",
                "name": "GB - วีแชทเพย์"
            },
            {
                "code": "en",
                "name": "GB - WeChat Pay"
            }
        ],
        "qrtype": 135
    },
    {
        "code": "XENDITTHAIQR",
        "logo": "https://raw.githubusercontent.com/smlsoft/dedepos_template/main/img/qrcode/promptpay.jpeg",
        "qrnames": [
            {
                "code": "th",
                "name": "XENDIT - พร้อมเพย์"
            },
            {
                "code": "en",
                "name": "XENDIT - Promptpay"
            }
        ],
        "qrtype": 201
    },
    {
        "code": "SMLPROMPTPAY",
        "logo": "https://raw.githubusercontent.com/smlsoft/dedepos_template/main/img/qrcode/sml.jpeg",
        "qrnames": [
            {
                "code": "th",
                "name": "SML - พร้อมเพย์"
            },
            {
                "code": "en",
                "name": "SML - Promptpay"
            }
        ],
        "qrtype": 301
    },
    {
        "code": "SMLCREDIT",
        "logo": "https://raw.githubusercontent.com/smlsoft/dedepos_template/main/img/qrcode/sml.jpeg",
        "qrnames": [
            {
                "code": "th",
                "name": "SML - เครดิต"
            },
            {
                "code": "en",
                "name": "SML - Credit"
            }
        ],
        "qrtype": 302
    }
]